mpt_api_client/__init__.py
mpt_api_client/constants.py
mpt_api_client/exceptions.py
mpt_api_client/mpt_client.py
mpt_api_client/py.typed
mpt_api_client/http/__init__.py
mpt_api_client/http/async_client.py
mpt_api_client/http/async_service.py
mpt_api_client/http/base_service.py
mpt_api_client/http/client.py
mpt_api_client/http/mixins.py
mpt_api_client/http/query_state.py
mpt_api_client/http/service.py
mpt_api_client/http/types.py
mpt_api_client/models/__init__.py
mpt_api_client/models/collection.py
mpt_api_client/models/file_model.py
mpt_api_client/models/meta.py
mpt_api_client/models/model.py
mpt_api_client/resources/__init__.py
mpt_api_client/resources/accounts/__init__.py
mpt_api_client/resources/accounts/account.py
mpt_api_client/resources/accounts/account_user_groups.py
mpt_api_client/resources/accounts/account_users.py
mpt_api_client/resources/accounts/accounts.py
mpt_api_client/resources/accounts/accounts_user_groups.py
mpt_api_client/resources/accounts/accounts_users.py
mpt_api_client/resources/accounts/api_tokens.py
mpt_api_client/resources/accounts/buyers.py
mpt_api_client/resources/accounts/cloud_tenants.py
mpt_api_client/resources/accounts/erp_links.py
mpt_api_client/resources/accounts/licensees.py
mpt_api_client/resources/accounts/mixins.py
mpt_api_client/resources/accounts/modules.py
mpt_api_client/resources/accounts/sellers.py
mpt_api_client/resources/accounts/user_groups.py
mpt_api_client/resources/accounts/users.py
mpt_api_client/resources/audit/__init__.py
mpt_api_client/resources/audit/audit.py
mpt_api_client/resources/audit/event_types.py
mpt_api_client/resources/audit/records.py
mpt_api_client/resources/billing/__init__.py
mpt_api_client/resources/billing/billing.py
mpt_api_client/resources/billing/credit_memo_attachments.py
mpt_api_client/resources/billing/credit_memos.py
mpt_api_client/resources/billing/custom_ledger_attachments.py
mpt_api_client/resources/billing/custom_ledger_charges.py
mpt_api_client/resources/billing/custom_ledgers.py
mpt_api_client-5.0.0.dist-info/METADATA
mpt_api_client-5.0.0.dist-info/WHEEL
mpt_api_client-5.0.0.dist-info/licenses/LICENSE
mpt_api_client-5.0.0.dist-info/RECORD
