Metadata-Version: 2.4
Name: mpt-api-client
Version: 5.0.0
Summary: SoftwareOne Marketplace API Client for Python
Author: SoftwareOne AG
License: Apache-2.0 license
License-File: LICENSE
Keywords: client,marketplace,openapi,softwareone
Classifier: Development Status :: 5 - Production/Stable
Classifier: Environment :: Console
Classifier: Operating System :: POSIX :: Linux
Classifier: Programming Language :: Python :: 3.12
Classifier: Topic :: Utilities
Requires-Python: <4,>=3.12
Requires-Dist: httpx==0.28.*
Requires-Dist: python-box>=7.3.2
